{
  "ts": "2025-12-02T18:57:43.343Z",
  "frameId": 1715,
  "motionPercent": 64.6432,
  "rois": [
    {
      "bbox": [
        237,
        346,
        310,
        443
      ]
    },
    {
      "bbox": [
        117,
        179,
        181,
        218
      ]
    },
    {
      "bbox": [
        111,
        102,
        158,
        139
      ]
    },
    {
      "bbox": [
        286,
        55,
        335,
        105
      ]
    },
    {
      "bbox": [
        126,
        30,
        185,
        110
      ]
    },
    {
      "bbox": [
        344,
        14,
        382,
        64
      ]
    },
    {
      "bbox": [
        0,
        0,
        640,
        480
      ]
    },
    {
      "bbox": [
        489,
        62,
        548,
        121
      ]
    },
    {
      "bbox": [
        181,
        285,
        371,
        475
      ]
    }
  ]
}