{
  "ts": "2025-12-21T18:19:25.007Z",
  "frameId": 93415,
  "motionPercent": 57.5758,
  "rois": [
    {
      "bbox": [
        555,
        452,
        638,
        480
      ]
    },
    {
      "bbox": [
        184,
        373,
        231,
        420
      ]
    },
    {
      "bbox": [
        263,
        345,
        370,
        409
      ]
    },
    {
      "bbox": [
        408,
        342,
        640,
        462
      ]
    },
    {
      "bbox": [
        514,
        314,
        551,
        345
      ]
    },
    {
      "bbox": [
        292,
        273,
        378,
        306
      ]
    },
    {
      "bbox": [
        580,
        86,
        640,
        133
      ]
    },
    {
      "bbox": [
        546,
        0,
        640,
        114
      ]
    },
    {
      "bbox": [
        491,
        0,
        525,
        47
      ]
    },
    {
      "bbox": [
        0,
        0,
        640,
        472
      ]
    }
  ]
}