{
  "ts": "2025-12-03T15:54:20.393Z",
  "frameId": 80,
  "motionPercent": 67.9023,
  "rois": [
    {
      "bbox": [
        98,
        264,
        143,
        303
      ]
    },
    {
      "bbox": [
        349,
        216,
        384,
        255
      ]
    },
    {
      "bbox": [
        112,
        172,
        145,
        218
      ]
    },
    {
      "bbox": [
        388,
        57,
        440,
        107
      ]
    },
    {
      "bbox": [
        182,
        52,
        235,
        89
      ]
    },
    {
      "bbox": [
        449,
        45,
        481,
        83
      ]
    },
    {
      "bbox": [
        0,
        0,
        640,
        480
      ]
    },
    {
      "bbox": [
        250,
        217,
        465,
        432
      ]
    }
  ]
}