{
  "ts": "2025-12-03T16:09:24.650Z",
  "frameId": 9480,
  "motionPercent": 23.4473,
  "rois": [
    {
      "bbox": [
        535,
        440,
        571,
        480
      ]
    },
    {
      "bbox": [
        317,
        373,
        355,
        419
      ]
    },
    {
      "bbox": [
        603,
        324,
        640,
        456
      ]
    },
    {
      "bbox": [
        218,
        145,
        472,
        480
      ]
    },
    {
      "bbox": [
        459,
        125,
        640,
        473
      ]
    },
    {
      "bbox": [
        563,
        123,
        639,
        171
      ]
    },
    {
      "bbox": [
        213,
        82,
        640,
        172
      ]
    },
    {
      "bbox": [
        534,
        34,
        580,
        66
      ]
    },
    {
      "bbox": [
        263,
        307,
        425,
        469
      ]
    }
  ]
}