{
  "ts": "2025-12-02T19:04:21.392Z",
  "frameId": 1815,
  "motionPercent": 41.0033,
  "rois": [
    {
      "bbox": [
        0,
        411,
        25,
        480
      ]
    },
    {
      "bbox": [
        352,
        366,
        429,
        463
      ]
    },
    {
      "bbox": [
        329,
        348,
        368,
        397
      ]
    },
    {
      "bbox": [
        340,
        321,
        407,
        349
      ]
    },
    {
      "bbox": [
        0,
        194,
        53,
        409
      ]
    },
    {
      "bbox": [
        0,
        52,
        50,
        203
      ]
    },
    {
      "bbox": [
        102,
        38,
        640,
        480
      ]
    },
    {
      "bbox": [
        190,
        25,
        220,
        62
      ]
    },
    {
      "bbox": [
        247,
        0,
        367,
        17
      ]
    },
    {
      "bbox": [
        174,
        0,
        224,
        27
      ]
    },
    {
      "bbox": [
        0,
        0,
        108,
        49
      ]
    },
    {
      "bbox": [
        492,
        63,
        549,
        120
      ]
    }
  ]
}