{
  "ts": "2025-12-21T17:17:37.548Z",
  "frameId": 51165,
  "motionPercent": 42.7992,
  "rois": [
    {
      "bbox": [
        148,
        446,
        187,
        480
      ]
    },
    {
      "bbox": [
        320,
        404,
        369,
        434
      ]
    },
    {
      "bbox": [
        104,
        382,
        192,
        438
      ]
    },
    {
      "bbox": [
        102,
        358,
        160,
        385
      ]
    },
    {
      "bbox": [
        482,
        331,
        640,
        480
      ]
    },
    {
      "bbox": [
        608,
        329,
        640,
        367
      ]
    },
    {
      "bbox": [
        586,
        273,
        640,
        343
      ]
    },
    {
      "bbox": [
        552,
        265,
        602,
        303
      ]
    },
    {
      "bbox": [
        597,
        248,
        640,
        284
      ]
    },
    {
      "bbox": [
        573,
        219,
        616,
        259
      ]
    },
    {
      "bbox": [
        76,
        214,
        118,
        257
      ]
    },
    {
      "bbox": [
        448,
        208,
        492,
        255
      ]
    },
    {
      "bbox": [
        0,
        195,
        126,
        480
      ]
    },
    {
      "bbox": [
        588,
        194,
        640,
        246
      ]
    },
    {
      "bbox": [
        0,
        155,
        56,
        194
      ]
    },
    {
      "bbox": [
        50,
        111,
        113,
        164
      ]
    },
    {
      "bbox": [
        478,
        96,
        563,
        144
      ]
    },
    {
      "bbox": [
        131,
        65,
        164,
        111
      ]
    },
    {
      "bbox": [
        462,
        0,
        640,
        190
      ]
    },
    {
      "bbox": [
        0,
        0,
        499,
        154
      ]
    }
  ]
}