{
  "ts": "2025-12-03T15:58:54.812Z",
  "frameId": 2840,
  "motionPercent": 10.5859,
  "rois": [
    {
      "bbox": [
        182,
        451,
        266,
        480
      ]
    },
    {
      "bbox": [
        253,
        423,
        309,
        480
      ]
    },
    {
      "bbox": [
        328,
        341,
        363,
        394
      ]
    },
    {
      "bbox": [
        551,
        336,
        615,
        386
      ]
    },
    {
      "bbox": [
        429,
        257,
        462,
        377
      ]
    },
    {
      "bbox": [
        461,
        253,
        539,
        323
      ]
    },
    {
      "bbox": [
        188,
        220,
        294,
        449
      ]
    },
    {
      "bbox": [
        180,
        191,
        256,
        223
      ]
    },
    {
      "bbox": [
        453,
        190,
        640,
        249
      ]
    },
    {
      "bbox": [
        514,
        186,
        572,
        229
      ]
    },
    {
      "bbox": [
        582,
        176,
        640,
        221
      ]
    },
    {
      "bbox": [
        250,
        162,
        431,
        219
      ]
    },
    {
      "bbox": [
        438,
        137,
        640,
        187
      ]
    },
    {
      "bbox": [
        488,
        99,
        528,
        129
      ]
    }
  ]
}