{
  "ts": "2025-12-03T16:09:34.542Z",
  "frameId": 9575,
  "motionPercent": 72.766,
  "rois": [
    {
      "bbox": [
        323,
        316,
        376,
        376
      ]
    },
    {
      "bbox": [
        313,
        269,
        362,
        325
      ]
    },
    {
      "bbox": [
        143,
        260,
        207,
        343
      ]
    },
    {
      "bbox": [
        173,
        156,
        218,
        212
      ]
    },
    {
      "bbox": [
        151,
        75,
        221,
        137
      ]
    },
    {
      "bbox": [
        439,
        62,
        470,
        105
      ]
    },
    {
      "bbox": [
        402,
        52,
        443,
        95
      ]
    },
    {
      "bbox": [
        382,
        16,
        439,
        58
      ]
    },
    {
      "bbox": [
        0,
        0,
        640,
        480
      ]
    },
    {
      "bbox": [
        263,
        317,
        417,
        471
      ]
    }
  ]
}