{
  "ts": "2025-12-21T16:12:18.365Z",
  "frameId": 6090,
  "motionPercent": 22.9753,
  "rois": [
    {
      "bbox": [
        333,
        374,
        410,
        405
      ]
    },
    {
      "bbox": [
        47,
        371,
        137,
        382
      ]
    },
    {
      "bbox": [
        359,
        345,
        430,
        387
      ]
    },
    {
      "bbox": [
        322,
        318,
        419,
        382
      ]
    },
    {
      "bbox": [
        344,
        263,
        404,
        322
      ]
    },
    {
      "bbox": [
        259,
        203,
        304,
        348
      ]
    },
    {
      "bbox": [
        0,
        181,
        253,
        202
      ]
    },
    {
      "bbox": [
        400,
        144,
        466,
        229
      ]
    },
    {
      "bbox": [
        261,
        71,
        340,
        236
      ]
    },
    {
      "bbox": [
        243,
        38,
        348,
        78
      ]
    },
    {
      "bbox": [
        0,
        10,
        92,
        64
      ]
    },
    {
      "bbox": [
        518,
        0,
        640,
        307
      ]
    },
    {
      "bbox": [
        366,
        0,
        567,
        480
      ]
    },
    {
      "bbox": [
        249,
        171,
        525,
        447
      ]
    }
  ]
}