{
  "ts": "2025-12-21T17:08:26.436Z",
  "frameId": 45055,
  "motionPercent": 11.3418,
  "rois": [
    {
      "bbox": [
        253,
        417,
        280,
        475
      ]
    },
    {
      "bbox": [
        522,
        164,
        564,
        424
      ]
    },
    {
      "bbox": [
        531,
        74,
        559,
        126
      ]
    },
    {
      "bbox": [
        376,
        0,
        487,
        40
      ]
    },
    {
      "bbox": [
        126,
        0,
        372,
        480
      ]
    }
  ]
}