{
  "ts": "2025-12-03T16:04:42.249Z",
  "frameId": 6435,
  "motionPercent": 7.6481,
  "rois": [
    {
      "bbox": [
        536,
        402,
        578,
        480
      ]
    },
    {
      "bbox": [
        551,
        359,
        614,
        409
      ]
    },
    {
      "bbox": [
        521,
        236,
        640,
        357
      ]
    },
    {
      "bbox": [
        540,
        202,
        570,
        244
      ]
    },
    {
      "bbox": [
        581,
        199,
        640,
        242
      ]
    },
    {
      "bbox": [
        496,
        123,
        640,
        195
      ]
    },
    {
      "bbox": [
        182,
        111,
        474,
        480
      ]
    },
    {
      "bbox": [
        544,
        341,
        609,
        406
      ]
    }
  ]
}