{
  "ts": "2025-12-21T18:01:53.657Z",
  "frameId": 81200,
  "motionPercent": 58.0104,
  "rois": [
    {
      "bbox": [
        0,
        397,
        58,
        426
      ]
    },
    {
      "bbox": [
        0,
        26,
        640,
        480
      ]
    },
    {
      "bbox": [
        438,
        0,
        640,
        51
      ]
    },
    {
      "bbox": [
        46,
        0,
        255,
        44
      ]
    },
    {
      "bbox": [
        202,
        74,
        268,
        140
      ]
    }
  ]
}