{
  "ts": "2025-12-21T17:17:37.980Z",
  "frameId": 51170,
  "motionPercent": 55.5534,
  "rois": [
    {
      "bbox": [
        167,
        452,
        219,
        480
      ]
    },
    {
      "bbox": [
        224,
        440,
        283,
        468
      ]
    },
    {
      "bbox": [
        288,
        436,
        323,
        467
      ]
    },
    {
      "bbox": [
        274,
        373,
        325,
        418
      ]
    },
    {
      "bbox": [
        328,
        369,
        359,
        412
      ]
    },
    {
      "bbox": [
        83,
        352,
        169,
        401
      ]
    },
    {
      "bbox": [
        428,
        304,
        477,
        361
      ]
    },
    {
      "bbox": [
        305,
        285,
        362,
        331
      ]
    },
    {
      "bbox": [
        81,
        284,
        146,
        330
      ]
    },
    {
      "bbox": [
        183,
        263,
        226,
        306
      ]
    },
    {
      "bbox": [
        370,
        226,
        513,
        286
      ]
    },
    {
      "bbox": [
        317,
        215,
        368,
        253
      ]
    },
    {
      "bbox": [
        524,
        202,
        595,
        245
      ]
    },
    {
      "bbox": [
        90,
        202,
        145,
        229
      ]
    },
    {
      "bbox": [
        126,
        157,
        182,
        201
      ]
    },
    {
      "bbox": [
        338,
        144,
        393,
        209
      ]
    },
    {
      "bbox": [
        141,
        125,
        196,
        156
      ]
    },
    {
      "bbox": [
        467,
        94,
        523,
        145
      ]
    },
    {
      "bbox": [
        431,
        43,
        476,
        103
      ]
    },
    {
      "bbox": [
        336,
        24,
        382,
        65
      ]
    },
    {
      "bbox": [
        217,
        24,
        248,
        65
      ]
    },
    {
      "bbox": [
        260,
        0,
        640,
        480
      ]
    },
    {
      "bbox": [
        0,
        0,
        259,
        480
      ]
    }
  ]
}