{
  "ts": "2025-12-02T18:22:08.944Z",
  "frameId": 11760,
  "motionPercent": 61.1406,
  "rois": [
    {
      "bbox": [
        260,
        450,
        327,
        480
      ]
    },
    {
      "bbox": [
        400,
        326,
        472,
        401
      ]
    },
    {
      "bbox": [
        219,
        326,
        285,
        360
      ]
    },
    {
      "bbox": [
        194,
        266,
        272,
        327
      ]
    },
    {
      "bbox": [
        164,
        174,
        222,
        266
      ]
    },
    {
      "bbox": [
        212,
        133,
        280,
        164
      ]
    },
    {
      "bbox": [
        235,
        53,
        283,
        99
      ]
    },
    {
      "bbox": [
        179,
        52,
        213,
        103
      ]
    },
    {
      "bbox": [
        283,
        28,
        335,
        69
      ]
    },
    {
      "bbox": [
        220,
        0,
        307,
        72
      ]
    },
    {
      "bbox": [
        0,
        0,
        640,
        480
      ]
    },
    {
      "bbox": [
        287,
        278,
        475,
        466
      ]
    }
  ]
}