{
  "ts": "2025-12-21T17:36:50.738Z",
  "frameId": 64115,
  "motionPercent": 11.5312,
  "rois": [
    {
      "bbox": [
        358,
        454,
        446,
        480
      ]
    },
    {
      "bbox": [
        346,
        413,
        640,
        480
      ]
    },
    {
      "bbox": [
        468,
        260,
        508,
        299
      ]
    },
    {
      "bbox": [
        522,
        211,
        552,
        251
      ]
    },
    {
      "bbox": [
        391,
        0,
        550,
        294
      ]
    }
  ]
}