{
  "ts": "2025-12-21T17:23:54.624Z",
  "frameId": 55435,
  "motionPercent": 7.4717,
  "rois": [
    {
      "bbox": [
        276,
        290,
        395,
        480
      ]
    },
    {
      "bbox": [
        509,
        62,
        592,
        141
      ]
    },
    {
      "bbox": [
        221,
        43,
        322,
        413
      ]
    },
    {
      "bbox": [
        550,
        40,
        640,
        84
      ]
    },
    {
      "bbox": [
        324,
        20,
        415,
        52
      ]
    }
  ]
}