{
  "ts": "2025-12-02T18:47:29.555Z",
  "frameId": 28945,
  "motionPercent": 40.569,
  "rois": [
    {
      "bbox": [
        0,
        433,
        25,
        480
      ]
    },
    {
      "bbox": [
        290,
        347,
        326,
        403
      ]
    },
    {
      "bbox": [
        0,
        48,
        69,
        415
      ]
    },
    {
      "bbox": [
        125,
        0,
        640,
        480
      ]
    },
    {
      "bbox": [
        256,
        0,
        377,
        11
      ]
    },
    {
      "bbox": [
        0,
        0,
        231,
        57
      ]
    },
    {
      "bbox": [
        221,
        280,
        403,
        462
      ]
    }
  ]
}