{
  "ts": "2025-12-02T18:41:59.205Z",
  "frameId": 25285,
  "motionPercent": 62.0697,
  "rois": [
    {
      "bbox": [
        357,
        394,
        401,
        442
      ]
    },
    {
      "bbox": [
        297,
        352,
        369,
        451
      ]
    },
    {
      "bbox": [
        326,
        266,
        425,
        337
      ]
    },
    {
      "bbox": [
        139,
        110,
        183,
        156
      ]
    },
    {
      "bbox": [
        398,
        0,
        435,
        79
      ]
    },
    {
      "bbox": [
        229,
        0,
        369,
        54
      ]
    },
    {
      "bbox": [
        0,
        0,
        640,
        480
      ]
    },
    {
      "bbox": [
        253,
        298,
        429,
        474
      ]
    }
  ]
}