{
  "ts": "2025-12-02T18:46:25.306Z",
  "frameId": 28230,
  "motionPercent": 2.4287,
  "rois": [
    {
      "bbox": [
        18,
        400,
        233,
        480
      ]
    },
    {
      "bbox": [
        417,
        254,
        473,
        442
      ]
    },
    {
      "bbox": [
        283,
        181,
        453,
        411
      ]
    },
    {
      "bbox": [
        490,
        61,
        550,
        121
      ]
    },
    {
      "bbox": [
        293,
        265,
        481,
        453
      ]
    }
  ]
}