{
  "ts": "2025-12-02T18:42:52.497Z",
  "frameId": 25870,
  "motionPercent": 61.1442,
  "rois": [
    {
      "bbox": [
        194,
        376,
        248,
        415
      ]
    },
    {
      "bbox": [
        109,
        346,
        145,
        394
      ]
    },
    {
      "bbox": [
        326,
        342,
        412,
        467
      ]
    },
    {
      "bbox": [
        359,
        271,
        419,
        334
      ]
    },
    {
      "bbox": [
        146,
        265,
        180,
        315
      ]
    },
    {
      "bbox": [
        79,
        237,
        122,
        279
      ]
    },
    {
      "bbox": [
        162,
        168,
        226,
        217
      ]
    },
    {
      "bbox": [
        24,
        126,
        89,
        216
      ]
    },
    {
      "bbox": [
        0,
        0,
        640,
        480
      ]
    },
    {
      "bbox": [
        249,
        0,
        361,
        27
      ]
    },
    {
      "bbox": [
        0,
        0,
        230,
        199
      ]
    },
    {
      "bbox": [
        284,
        278,
        478,
        472
      ]
    }
  ]
}