{
  "ts": "2025-12-02T18:47:55.636Z",
  "frameId": 29230,
  "motionPercent": 62.3122,
  "rois": [
    {
      "bbox": [
        181,
        437,
        235,
        480
      ]
    },
    {
      "bbox": [
        258,
        335,
        324,
        406
      ]
    },
    {
      "bbox": [
        270,
        289,
        307,
        323
      ]
    },
    {
      "bbox": [
        56,
        262,
        99,
        305
      ]
    },
    {
      "bbox": [
        408,
        192,
        449,
        233
      ]
    },
    {
      "bbox": [
        188,
        165,
        225,
        204
      ]
    },
    {
      "bbox": [
        160,
        84,
        207,
        143
      ]
    },
    {
      "bbox": [
        366,
        58,
        411,
        111
      ]
    },
    {
      "bbox": [
        238,
        0,
        388,
        37
      ]
    },
    {
      "bbox": [
        0,
        0,
        640,
        480
      ]
    },
    {
      "bbox": [
        489,
        60,
        549,
        120
      ]
    },
    {
      "bbox": [
        206,
        274,
        388,
        456
      ]
    }
  ]
}