{
  "ts": "2025-12-02T18:46:13.012Z",
  "frameId": 28090,
  "motionPercent": 34.5889,
  "rois": [
    {
      "bbox": [
        0,
        426,
        32,
        480
      ]
    },
    {
      "bbox": [
        169,
        365,
        193,
        480
      ]
    },
    {
      "bbox": [
        0,
        201,
        62,
        411
      ]
    },
    {
      "bbox": [
        0,
        54,
        53,
        201
      ]
    },
    {
      "bbox": [
        0,
        8,
        73,
        50
      ]
    },
    {
      "bbox": [
        245,
        0,
        640,
        480
      ]
    },
    {
      "bbox": [
        255,
        0,
        383,
        16
      ]
    },
    {
      "bbox": [
        121,
        0,
        232,
        65
      ]
    },
    {
      "bbox": [
        491,
        62,
        548,
        119
      ]
    },
    {
      "bbox": [
        465,
        285,
        551,
        371
      ]
    }
  ]
}