{
  "ts": "2025-12-02T18:46:41.312Z",
  "frameId": 28410,
  "motionPercent": 57.3311,
  "rois": [
    {
      "bbox": [
        478,
        411,
        555,
        480
      ]
    },
    {
      "bbox": [
        261,
        275,
        320,
        323
      ]
    },
    {
      "bbox": [
        118,
        274,
        182,
        316
      ]
    },
    {
      "bbox": [
        74,
        231,
        107,
        283
      ]
    },
    {
      "bbox": [
        23,
        160,
        54,
        199
      ]
    },
    {
      "bbox": [
        167,
        157,
        232,
        318
      ]
    },
    {
      "bbox": [
        384,
        126,
        434,
        174
      ]
    },
    {
      "bbox": [
        275,
        26,
        313,
        79
      ]
    },
    {
      "bbox": [
        236,
        0,
        385,
        24
      ]
    },
    {
      "bbox": [
        0,
        0,
        640,
        480
      ]
    },
    {
      "bbox": [
        488,
        59,
        549,
        120
      ]
    }
  ]
}