{
  "ts": "2025-12-02T18:43:39.775Z",
  "frameId": 26400,
  "motionPercent": 67.4827,
  "rois": [
    {
      "bbox": [
        256,
        448,
        330,
        480
      ]
    },
    {
      "bbox": [
        297,
        391,
        349,
        417
      ]
    },
    {
      "bbox": [
        378,
        355,
        415,
        399
      ]
    },
    {
      "bbox": [
        418,
        318,
        478,
        414
      ]
    },
    {
      "bbox": [
        387,
        305,
        442,
        365
      ]
    },
    {
      "bbox": [
        360,
        256,
        424,
        288
      ]
    },
    {
      "bbox": [
        312,
        172,
        336,
        232
      ]
    },
    {
      "bbox": [
        0,
        0,
        640,
        480
      ]
    }
  ]
}