{
  "ts": "2025-12-02T18:48:02.492Z",
  "frameId": 29300,
  "motionPercent": 63.0488,
  "rois": [
    {
      "bbox": [
        176,
        443,
        252,
        480
      ]
    },
    {
      "bbox": [
        263,
        411,
        339,
        463
      ]
    },
    {
      "bbox": [
        336,
        332,
        380,
        365
      ]
    },
    {
      "bbox": [
        270,
        316,
        330,
        413
      ]
    },
    {
      "bbox": [
        118,
        239,
        180,
        283
      ]
    },
    {
      "bbox": [
        182,
        87,
        219,
        151
      ]
    },
    {
      "bbox": [
        254,
        0,
        404,
        21
      ]
    },
    {
      "bbox": [
        0,
        0,
        640,
        480
      ]
    },
    {
      "bbox": [
        489,
        60,
        549,
        120
      ]
    },
    {
      "bbox": [
        208,
        277,
        387,
        456
      ]
    }
  ]
}