{
  "ts": "2025-12-02T19:03:41.685Z",
  "frameId": 1400,
  "motionPercent": 38.2881,
  "rois": [
    {
      "bbox": [
        0,
        430,
        33,
        480
      ]
    },
    {
      "bbox": [
        381,
        363,
        439,
        451
      ]
    },
    {
      "bbox": [
        0,
        253,
        80,
        399
      ]
    },
    {
      "bbox": [
        175,
        234,
        203,
        446
      ]
    },
    {
      "bbox": [
        0,
        194,
        60,
        290
      ]
    },
    {
      "bbox": [
        0,
        51,
        51,
        200
      ]
    },
    {
      "bbox": [
        147,
        36,
        640,
        480
      ]
    },
    {
      "bbox": [
        440,
        0,
        498,
        29
      ]
    },
    {
      "bbox": [
        256,
        0,
        370,
        14
      ]
    },
    {
      "bbox": [
        0,
        0,
        226,
        57
      ]
    }
  ]
}