{
  "ts": "2025-12-02T19:01:58.200Z",
  "frameId": 285,
  "motionPercent": 30.7754,
  "rois": [
    {
      "bbox": [
        301,
        323,
        345,
        379
      ]
    },
    {
      "bbox": [
        0,
        301,
        52,
        399
      ]
    },
    {
      "bbox": [
        0,
        256,
        36,
        301
      ]
    },
    {
      "bbox": [
        0,
        196,
        49,
        230
      ]
    },
    {
      "bbox": [
        92,
        171,
        479,
        480
      ]
    },
    {
      "bbox": [
        0,
        69,
        21,
        136
      ]
    },
    {
      "bbox": [
        0,
        55,
        46,
        201
      ]
    },
    {
      "bbox": [
        448,
        42,
        640,
        480
      ]
    },
    {
      "bbox": [
        191,
        26,
        219,
        58
      ]
    },
    {
      "bbox": [
        488,
        60,
        549,
        121
      ]
    },
    {
      "bbox": [
        232,
        255,
        432,
        455
      ]
    }
  ]
}