{
  "ts": "2025-12-21T18:18:14.911Z",
  "frameId": 92610,
  "motionPercent": 60.8844,
  "rois": [
    {
      "bbox": [
        551,
        333,
        619,
        418
      ]
    },
    {
      "bbox": [
        595,
        330,
        640,
        369
      ]
    },
    {
      "bbox": [
        600,
        237,
        640,
        315
      ]
    },
    {
      "bbox": [
        607,
        189,
        640,
        238
      ]
    },
    {
      "bbox": [
        533,
        165,
        559,
        252
      ]
    },
    {
      "bbox": [
        586,
        136,
        640,
        188
      ]
    },
    {
      "bbox": [
        604,
        86,
        640,
        140
      ]
    },
    {
      "bbox": [
        493,
        7,
        554,
        159
      ]
    },
    {
      "bbox": [
        536,
        0,
        640,
        109
      ]
    },
    {
      "bbox": [
        0,
        0,
        640,
        480
      ]
    },
    {
      "bbox": [
        241,
        141,
        493,
        393
      ]
    }
  ]
}