{
  "ts": "2025-12-21T18:03:29.182Z",
  "frameId": 82230,
  "motionPercent": 31.888,
  "rois": [
    {
      "bbox": [
        5,
        259,
        47,
        307
      ]
    },
    {
      "bbox": [
        14,
        162,
        55,
        215
      ]
    },
    {
      "bbox": [
        55,
        156,
        350,
        480
      ]
    },
    {
      "bbox": [
        221,
        0,
        376,
        245
      ]
    },
    {
      "bbox": [
        143,
        0,
        190,
        138
      ]
    }
  ]
}