{
  "ts": "2025-12-02T18:55:22.173Z",
  "frameId": 215,
  "motionPercent": 2.8132,
  "rois": [
    {
      "bbox": [
        358,
        221,
        395,
        435
      ]
    },
    {
      "bbox": [
        126,
        185,
        262,
        480
      ]
    },
    {
      "bbox": [
        264,
        176,
        381,
        224
      ]
    },
    {
      "bbox": [
        491,
        62,
        549,
        120
      ]
    },
    {
      "bbox": [
        203,
        256,
        397,
        450
      ]
    }
  ]
}