{
  "ts": "2025-12-02T18:04:46.088Z",
  "frameId": 845,
  "motionPercent": 37.8164,
  "rois": [
    {
      "bbox": [
        260,
        325,
        331,
        413
      ]
    },
    {
      "bbox": [
        0,
        191,
        39,
        391
      ]
    },
    {
      "bbox": [
        0,
        42,
        38,
        146
      ]
    },
    {
      "bbox": [
        100,
        17,
        640,
        480
      ]
    },
    {
      "bbox": [
        151,
        0,
        212,
        49
      ]
    },
    {
      "bbox": [
        62,
        0,
        150,
        29
      ]
    },
    {
      "bbox": [
        206,
        260,
        407,
        461
      ]
    }
  ]
}