{
  "ts": "2025-12-21T16:14:25.538Z",
  "frameId": 7570,
  "motionPercent": 69.3053,
  "rois": [
    {
      "bbox": [
        0,
        431,
        67,
        468
      ]
    },
    {
      "bbox": [
        74,
        371,
        130,
        416
      ]
    },
    {
      "bbox": [
        186,
        346,
        236,
        383
      ]
    },
    {
      "bbox": [
        28,
        270,
        93,
        331
      ]
    },
    {
      "bbox": [
        74,
        267,
        109,
        309
      ]
    },
    {
      "bbox": [
        0,
        262,
        167,
        393
      ]
    },
    {
      "bbox": [
        63,
        49,
        116,
        98
      ]
    },
    {
      "bbox": [
        0,
        0,
        640,
        480
      ]
    },
    {
      "bbox": [
        0,
        0,
        105,
        148
      ]
    },
    {
      "bbox": [
        529,
        178,
        622,
        271
      ]
    }
  ]
}