{
  "ts": "2025-12-21T16:43:50.858Z",
  "frameId": 28010,
  "motionPercent": 74.4069,
  "rois": [
    {
      "bbox": [
        0,
        450,
        31,
        480
      ]
    },
    {
      "bbox": [
        461,
        371,
        530,
        409
      ]
    },
    {
      "bbox": [
        405,
        252,
        451,
        324
      ]
    },
    {
      "bbox": [
        0,
        30,
        73,
        134
      ]
    },
    {
      "bbox": [
        0,
        0,
        640,
        480
      ]
    }
  ]
}