{
  "ts": "2025-12-03T16:04:27.031Z",
  "frameId": 6270,
  "motionPercent": 15.3213,
  "rois": [
    {
      "bbox": [
        465,
        429,
        515,
        480
      ]
    },
    {
      "bbox": [
        394,
        421,
        455,
        480
      ]
    },
    {
      "bbox": [
        298,
        364,
        327,
        413
      ]
    },
    {
      "bbox": [
        601,
        349,
        637,
        389
      ]
    },
    {
      "bbox": [
        446,
        333,
        477,
        407
      ]
    },
    {
      "bbox": [
        167,
        204,
        292,
        480
      ]
    },
    {
      "bbox": [
        509,
        196,
        567,
        238
      ]
    },
    {
      "bbox": [
        571,
        184,
        640,
        232
      ]
    },
    {
      "bbox": [
        245,
        173,
        451,
        420
      ]
    },
    {
      "bbox": [
        418,
        148,
        640,
        480
      ]
    },
    {
      "bbox": [
        479,
        111,
        520,
        140
      ]
    },
    {
      "bbox": [
        228,
        276,
        426,
        474
      ]
    }
  ]
}