{
  "ts": "2025-12-21T16:12:51.764Z",
  "frameId": 6475,
  "motionPercent": 8.835,
  "rois": [
    {
      "bbox": [
        179,
        425,
        210,
        480
      ]
    },
    {
      "bbox": [
        320,
        419,
        409,
        480
      ]
    },
    {
      "bbox": [
        313,
        379,
        357,
        429
      ]
    },
    {
      "bbox": [
        358,
        310,
        391,
        415
      ]
    },
    {
      "bbox": [
        311,
        268,
        351,
        358
      ]
    },
    {
      "bbox": [
        172,
        209,
        219,
        336
      ]
    },
    {
      "bbox": [
        177,
        101,
        210,
        188
      ]
    },
    {
      "bbox": [
        349,
        69,
        427,
        282
      ]
    },
    {
      "bbox": [
        174,
        168,
        443,
        437
      ]
    }
  ]
}