{
  "ts": "2025-12-21T16:43:47.799Z",
  "frameId": 27975,
  "motionPercent": 33.3079,
  "rois": [
    {
      "bbox": [
        566,
        420,
        640,
        480
      ]
    },
    {
      "bbox": [
        437,
        420,
        553,
        480
      ]
    },
    {
      "bbox": [
        179,
        412,
        331,
        480
      ]
    },
    {
      "bbox": [
        138,
        307,
        160,
        401
      ]
    },
    {
      "bbox": [
        298,
        293,
        319,
        414
      ]
    },
    {
      "bbox": [
        512,
        264,
        574,
        299
      ]
    },
    {
      "bbox": [
        298,
        238,
        325,
        290
      ]
    },
    {
      "bbox": [
        475,
        203,
        558,
        240
      ]
    },
    {
      "bbox": [
        175,
        137,
        291,
        357
      ]
    },
    {
      "bbox": [
        114,
        33,
        140,
        121
      ]
    },
    {
      "bbox": [
        333,
        26,
        640,
        472
      ]
    },
    {
      "bbox": [
        362,
        23,
        391,
        118
      ]
    },
    {
      "bbox": [
        359,
        0,
        443,
        67
      ]
    },
    {
      "bbox": [
        285,
        0,
        360,
        208
      ]
    },
    {
      "bbox": [
        204,
        0,
        268,
        91
      ]
    },
    {
      "bbox": [
        144,
        0,
        177,
        285
      ]
    }
  ]
}