{
  "ts": "2025-12-21T16:04:03.056Z",
  "frameId": 460,
  "motionPercent": 12.5651,
  "rois": [
    {
      "bbox": [
        509,
        357,
        562,
        395
      ]
    },
    {
      "bbox": [
        243,
        293,
        296,
        347
      ]
    },
    {
      "bbox": [
        227,
        94,
        305,
        209
      ]
    },
    {
      "bbox": [
        557,
        71,
        585,
        164
      ]
    },
    {
      "bbox": [
        590,
        42,
        619,
        109
      ]
    },
    {
      "bbox": [
        371,
        26,
        574,
        459
      ]
    },
    {
      "bbox": [
        53,
        7,
        97,
        77
      ]
    }
  ]
}