{
  "ts": "2025-12-21T16:48:21.804Z",
  "frameId": 31205,
  "motionPercent": 5.0332,
  "rois": [
    {
      "bbox": [
        0,
        347,
        111,
        360
      ]
    },
    {
      "bbox": [
        529,
        267,
        571,
        311
      ]
    },
    {
      "bbox": [
        482,
        256,
        510,
        390
      ]
    },
    {
      "bbox": [
        260,
        172,
        285,
        349
      ]
    },
    {
      "bbox": [
        482,
        141,
        572,
        255
      ]
    },
    {
      "bbox": [
        295,
        84,
        415,
        121
      ]
    },
    {
      "bbox": [
        271,
        236,
        500,
        465
      ]
    }
  ]
}