{
  "ts": "2025-12-03T15:58:20.259Z",
  "frameId": 2475,
  "motionPercent": 15.5179,
  "rois": [
    {
      "bbox": [
        183,
        439,
        231,
        480
      ]
    },
    {
      "bbox": [
        442,
        426,
        477,
        474
      ]
    },
    {
      "bbox": [
        476,
        417,
        587,
        480
      ]
    },
    {
      "bbox": [
        316,
        369,
        348,
        404
      ]
    },
    {
      "bbox": [
        187,
        368,
        231,
        437
      ]
    },
    {
      "bbox": [
        497,
        364,
        535,
        405
      ]
    },
    {
      "bbox": [
        254,
        308,
        305,
        467
      ]
    },
    {
      "bbox": [
        196,
        216,
        277,
        375
      ]
    },
    {
      "bbox": [
        517,
        213,
        640,
        421
      ]
    },
    {
      "bbox": [
        485,
        182,
        575,
        229
      ]
    },
    {
      "bbox": [
        578,
        172,
        640,
        217
      ]
    },
    {
      "bbox": [
        182,
        114,
        514,
        466
      ]
    },
    {
      "bbox": [
        476,
        98,
        639,
        181
      ]
    }
  ]
}