{
  "ts": "2025-12-03T16:11:28.543Z",
  "frameId": 10695,
  "motionPercent": 52.6608,
  "rois": [
    {
      "bbox": [
        0,
        401,
        48,
        467
      ]
    },
    {
      "bbox": [
        0,
        165,
        26,
        231
      ]
    },
    {
      "bbox": [
        41,
        151,
        93,
        181
      ]
    },
    {
      "bbox": [
        0,
        107,
        56,
        159
      ]
    },
    {
      "bbox": [
        60,
        97,
        96,
        151
      ]
    },
    {
      "bbox": [
        0,
        90,
        31,
        130
      ]
    },
    {
      "bbox": [
        0,
        30,
        640,
        480
      ]
    },
    {
      "bbox": [
        116,
        25,
        191,
        73
      ]
    },
    {
      "bbox": [
        58,
        12,
        88,
        69
      ]
    },
    {
      "bbox": [
        568,
        10,
        622,
        51
      ]
    },
    {
      "bbox": [
        172,
        8,
        214,
        45
      ]
    },
    {
      "bbox": [
        50,
        0,
        149,
        50
      ]
    },
    {
      "bbox": [
        0,
        0,
        79,
        103
      ]
    }
  ]
}