{
  "ts": "2025-12-03T16:05:07.346Z",
  "frameId": 6710,
  "motionPercent": 63.7507,
  "rois": [
    {
      "bbox": [
        320,
        414,
        358,
        455
      ]
    },
    {
      "bbox": [
        354,
        410,
        440,
        480
      ]
    },
    {
      "bbox": [
        384,
        393,
        433,
        439
      ]
    },
    {
      "bbox": [
        151,
        380,
        193,
        417
      ]
    },
    {
      "bbox": [
        473,
        374,
        497,
        421
      ]
    },
    {
      "bbox": [
        369,
        292,
        427,
        367
      ]
    },
    {
      "bbox": [
        113,
        262,
        173,
        303
      ]
    },
    {
      "bbox": [
        386,
        259,
        439,
        304
      ]
    },
    {
      "bbox": [
        335,
        258,
        392,
        299
      ]
    },
    {
      "bbox": [
        455,
        249,
        496,
        296
      ]
    },
    {
      "bbox": [
        103,
        211,
        135,
        257
      ]
    },
    {
      "bbox": [
        399,
        157,
        443,
        189
      ]
    },
    {
      "bbox": [
        346,
        145,
        398,
        192
      ]
    },
    {
      "bbox": [
        344,
        6,
        378,
        49
      ]
    },
    {
      "bbox": [
        269,
        0,
        321,
        63
      ]
    },
    {
      "bbox": [
        0,
        0,
        640,
        480
      ]
    },
    {
      "bbox": [
        544,
        340,
        604,
        400
      ]
    }
  ]
}