{
  "ts": "2025-12-02T18:22:54.820Z",
  "frameId": 12275,
  "motionPercent": 60.3662,
  "rois": [
    {
      "bbox": [
        282,
        448,
        335,
        480
      ]
    },
    {
      "bbox": [
        210,
        352,
        261,
        389
      ]
    },
    {
      "bbox": [
        358,
        283,
        420,
        332
      ]
    },
    {
      "bbox": [
        196,
        262,
        276,
        353
      ]
    },
    {
      "bbox": [
        176,
        132,
        223,
        217
      ]
    },
    {
      "bbox": [
        162,
        92,
        211,
        131
      ]
    },
    {
      "bbox": [
        277,
        20,
        369,
        80
      ]
    },
    {
      "bbox": [
        112,
        0,
        640,
        480
      ]
    },
    {
      "bbox": [
        222,
        0,
        317,
        46
      ]
    },
    {
      "bbox": [
        0,
        0,
        229,
        480
      ]
    },
    {
      "bbox": [
        294,
        279,
        483,
        468
      ]
    }
  ]
}