{
  "ts": "2025-12-02T18:37:32.150Z",
  "frameId": 22255,
  "motionPercent": 56.9043,
  "rois": [
    {
      "bbox": [
        387,
        381,
        487,
        478
      ]
    },
    {
      "bbox": [
        189,
        304,
        250,
        364
      ]
    },
    {
      "bbox": [
        256,
        298,
        316,
        329
      ]
    },
    {
      "bbox": [
        84,
        298,
        150,
        375
      ]
    },
    {
      "bbox": [
        225,
        256,
        269,
        301
      ]
    },
    {
      "bbox": [
        103,
        220,
        153,
        277
      ]
    },
    {
      "bbox": [
        78,
        135,
        121,
        201
      ]
    },
    {
      "bbox": [
        253,
        0,
        340,
        43
      ]
    },
    {
      "bbox": [
        0,
        0,
        640,
        480
      ]
    },
    {
      "bbox": [
        343,
        311,
        499,
        467
      ]
    }
  ]
}