{
  "ts": "2025-12-02T18:25:57.706Z",
  "frameId": 14335,
  "motionPercent": 55.1009,
  "rois": [
    {
      "bbox": [
        489,
        411,
        571,
        480
      ]
    },
    {
      "bbox": [
        288,
        389,
        352,
        443
      ]
    },
    {
      "bbox": [
        406,
        353,
        486,
        473
      ]
    },
    {
      "bbox": [
        470,
        306,
        526,
        385
      ]
    },
    {
      "bbox": [
        80,
        286,
        113,
        337
      ]
    },
    {
      "bbox": [
        194,
        285,
        247,
        334
      ]
    },
    {
      "bbox": [
        46,
        256,
        94,
        317
      ]
    },
    {
      "bbox": [
        117,
        192,
        155,
        247
      ]
    },
    {
      "bbox": [
        77,
        52,
        147,
        181
      ]
    },
    {
      "bbox": [
        0,
        0,
        640,
        480
      ]
    }
  ]
}