{
  "ts": "2025-12-02T18:38:11.741Z",
  "frameId": 22705,
  "motionPercent": 56.8659,
  "rois": [
    {
      "bbox": [
        504,
        455,
        551,
        480
      ]
    },
    {
      "bbox": [
        422,
        390,
        468,
        443
      ]
    },
    {
      "bbox": [
        331,
        312,
        374,
        381
      ]
    },
    {
      "bbox": [
        71,
        281,
        148,
        361
      ]
    },
    {
      "bbox": [
        310,
        277,
        373,
        331
      ]
    },
    {
      "bbox": [
        77,
        241,
        136,
        278
      ]
    },
    {
      "bbox": [
        135,
        237,
        172,
        279
      ]
    },
    {
      "bbox": [
        61,
        100,
        118,
        163
      ]
    },
    {
      "bbox": [
        383,
        13,
        430,
        45
      ]
    },
    {
      "bbox": [
        148,
        0,
        640,
        480
      ]
    },
    {
      "bbox": [
        239,
        0,
        368,
        33
      ]
    },
    {
      "bbox": [
        0,
        0,
        228,
        480
      ]
    }
  ]
}