{
  "ts": "2025-12-02T18:26:01.243Z",
  "frameId": 14375,
  "motionPercent": 56.1755,
  "rois": [
    {
      "bbox": [
        482,
        428,
        560,
        480
      ]
    },
    {
      "bbox": [
        264,
        278,
        304,
        333
      ]
    },
    {
      "bbox": [
        110,
        198,
        168,
        239
      ]
    },
    {
      "bbox": [
        67,
        182,
        114,
        249
      ]
    },
    {
      "bbox": [
        144,
        145,
        224,
        190
      ]
    },
    {
      "bbox": [
        188,
        0,
        640,
        480
      ]
    },
    {
      "bbox": [
        0,
        0,
        251,
        480
      ]
    }
  ]
}