{
  "ts": "2025-12-02T18:25:08.101Z",
  "frameId": 13755,
  "motionPercent": 61.7718,
  "rois": [
    {
      "bbox": [
        332,
        389,
        410,
        458
      ]
    },
    {
      "bbox": [
        112,
        280,
        175,
        322
      ]
    },
    {
      "bbox": [
        396,
        277,
        450,
        304
      ]
    },
    {
      "bbox": [
        229,
        199,
        268,
        232
      ]
    },
    {
      "bbox": [
        147,
        68,
        183,
        143
      ]
    },
    {
      "bbox": [
        0,
        0,
        640,
        480
      ]
    },
    {
      "bbox": [
        245,
        0,
        311,
        25
      ]
    },
    {
      "bbox": [
        0,
        0,
        263,
        448
      ]
    }
  ]
}