{
  "ts": "2025-12-02T18:34:18.717Z",
  "frameId": 20110,
  "motionPercent": 63.5361,
  "rois": [
    {
      "bbox": [
        214,
        360,
        248,
        403
      ]
    },
    {
      "bbox": [
        279,
        297,
        407,
        473
      ]
    },
    {
      "bbox": [
        282,
        254,
        362,
        343
      ]
    },
    {
      "bbox": [
        89,
        249,
        144,
        298
      ]
    },
    {
      "bbox": [
        180,
        77,
        213,
        116
      ]
    },
    {
      "bbox": [
        246,
        0,
        356,
        36
      ]
    },
    {
      "bbox": [
        0,
        0,
        640,
        480
      ]
    },
    {
      "bbox": [
        231,
        282,
        410,
        461
      ]
    }
  ]
}