{
  "ts": "2025-12-02T18:26:50.094Z",
  "frameId": 14940,
  "motionPercent": 34.8978,
  "rois": [
    {
      "bbox": [
        478,
        422,
        540,
        480
      ]
    },
    {
      "bbox": [
        401,
        266,
        456,
        316
      ]
    },
    {
      "bbox": [
        177,
        238,
        198,
        317
      ]
    },
    {
      "bbox": [
        0,
        195,
        52,
        394
      ]
    },
    {
      "bbox": [
        0,
        48,
        54,
        191
      ]
    },
    {
      "bbox": [
        186,
        21,
        217,
        55
      ]
    },
    {
      "bbox": [
        181,
        0,
        640,
        480
      ]
    },
    {
      "bbox": [
        46,
        0,
        220,
        37
      ]
    },
    {
      "bbox": [
        0,
        0,
        47,
        39
      ]
    }
  ]
}