{
  "ts": "2025-12-02T18:23:08.249Z",
  "frameId": 12430,
  "motionPercent": 60.4538,
  "rois": [
    {
      "bbox": [
        367,
        425,
        422,
        466
      ]
    },
    {
      "bbox": [
        200,
        397,
        249,
        427
      ]
    },
    {
      "bbox": [
        111,
        261,
        142,
        323
      ]
    },
    {
      "bbox": [
        78,
        255,
        109,
        287
      ]
    },
    {
      "bbox": [
        249,
        28,
        301,
        67
      ]
    },
    {
      "bbox": [
        250,
        0,
        341,
        84
      ]
    },
    {
      "bbox": [
        0,
        0,
        640,
        480
      ]
    },
    {
      "bbox": [
        296,
        281,
        483,
        468
      ]
    }
  ]
}