{
  "ts": "2025-12-02T18:35:09.621Z",
  "frameId": 20650,
  "motionPercent": 36.5225,
  "rois": [
    {
      "bbox": [
        161,
        385,
        185,
        480
      ]
    },
    {
      "bbox": [
        370,
        363,
        450,
        459
      ]
    },
    {
      "bbox": [
        0,
        299,
        49,
        399
      ]
    },
    {
      "bbox": [
        0,
        251,
        33,
        299
      ]
    },
    {
      "bbox": [
        0,
        198,
        52,
        299
      ]
    },
    {
      "bbox": [
        0,
        50,
        55,
        190
      ]
    },
    {
      "bbox": [
        185,
        22,
        217,
        57
      ]
    },
    {
      "bbox": [
        0,
        15,
        39,
        48
      ]
    },
    {
      "bbox": [
        34,
        8,
        114,
        35
      ]
    },
    {
      "bbox": [
        181,
        0,
        640,
        480
      ]
    },
    {
      "bbox": [
        340,
        311,
        500,
        471
      ]
    }
  ]
}