{
  "ts": "2025-12-21T16:43:21.233Z",
  "frameId": 27680,
  "motionPercent": 20.2168,
  "rois": [
    {
      "bbox": [
        361,
        307,
        417,
        395
      ]
    },
    {
      "bbox": [
        493,
        255,
        538,
        431
      ]
    },
    {
      "bbox": [
        469,
        251,
        503,
        287
      ]
    },
    {
      "bbox": [
        141,
        190,
        165,
        274
      ]
    },
    {
      "bbox": [
        175,
        171,
        290,
        303
      ]
    },
    {
      "bbox": [
        205,
        158,
        249,
        205
      ]
    },
    {
      "bbox": [
        151,
        113,
        347,
        480
      ]
    },
    {
      "bbox": [
        425,
        82,
        479,
        138
      ]
    },
    {
      "bbox": [
        365,
        78,
        424,
        107
      ]
    },
    {
      "bbox": [
        332,
        75,
        370,
        135
      ]
    },
    {
      "bbox": [
        297,
        38,
        345,
        121
      ]
    },
    {
      "bbox": [
        399,
        6,
        435,
        45
      ]
    },
    {
      "bbox": [
        212,
        0,
        241,
        62
      ]
    },
    {
      "bbox": [
        152,
        0,
        176,
        99
      ]
    },
    {
      "bbox": [
        282,
        211,
        535,
        464
      ]
    }
  ]
}