{
  "ts": "2025-12-21T16:03:26.606Z",
  "frameId": 60,
  "motionPercent": 64.9824,
  "rois": [
    {
      "bbox": [
        336,
        451,
        371,
        480
      ]
    },
    {
      "bbox": [
        150,
        429,
        210,
        480
      ]
    },
    {
      "bbox": [
        375,
        386,
        455,
        480
      ]
    },
    {
      "bbox": [
        0,
        379,
        149,
        480
      ]
    },
    {
      "bbox": [
        211,
        358,
        264,
        395
      ]
    },
    {
      "bbox": [
        223,
        310,
        390,
        480
      ]
    },
    {
      "bbox": [
        317,
        248,
        384,
        334
      ]
    },
    {
      "bbox": [
        304,
        224,
        360,
        256
      ]
    },
    {
      "bbox": [
        216,
        185,
        256,
        246
      ]
    },
    {
      "bbox": [
        32,
        156,
        99,
        240
      ]
    },
    {
      "bbox": [
        132,
        70,
        186,
        118
      ]
    },
    {
      "bbox": [
        0,
        0,
        640,
        480
      ]
    }
  ]
}