{
  "ts": "2025-12-21T18:21:11.718Z",
  "frameId": 94565,
  "motionPercent": 24.1611,
  "rois": [
    {
      "bbox": [
        0,
        222,
        26,
        297
      ]
    },
    {
      "bbox": [
        24,
        218,
        48,
        278
      ]
    },
    {
      "bbox": [
        46,
        180,
        83,
        262
      ]
    },
    {
      "bbox": [
        149,
        79,
        340,
        480
      ]
    },
    {
      "bbox": [
        0,
        53,
        176,
        480
      ]
    },
    {
      "bbox": [
        308,
        8,
        640,
        456
      ]
    },
    {
      "bbox": [
        569,
        0,
        640,
        80
      ]
    },
    {
      "bbox": [
        287,
        0,
        308,
        81
      ]
    },
    {
      "bbox": [
        246,
        124,
        531,
        409
      ]
    }
  ]
}