{
  "ts": "2025-12-21T18:03:12.961Z",
  "frameId": 82060,
  "motionPercent": 17.2663,
  "rois": [
    {
      "bbox": [
        153,
        314,
        177,
        374
      ]
    },
    {
      "bbox": [
        106,
        290,
        154,
        393
      ]
    },
    {
      "bbox": [
        146,
        230,
        179,
        278
      ]
    },
    {
      "bbox": [
        378,
        174,
        463,
        480
      ]
    },
    {
      "bbox": [
        448,
        0,
        640,
        480
      ]
    },
    {
      "bbox": [
        368,
        0,
        402,
        84
      ]
    },
    {
      "bbox": [
        204,
        76,
        267,
        139
      ]
    },
    {
      "bbox": [
        128,
        230,
        183,
        285
      ]
    }
  ]
}