{
  "ts": "2025-12-21T16:53:01.799Z",
  "frameId": 34405,
  "motionPercent": 32.3379,
  "rois": [
    {
      "bbox": [
        370,
        407,
        488,
        480
      ]
    },
    {
      "bbox": [
        102,
        352,
        151,
        404
      ]
    },
    {
      "bbox": [
        0,
        344,
        85,
        357
      ]
    },
    {
      "bbox": [
        78,
        115,
        120,
        145
      ]
    },
    {
      "bbox": [
        141,
        93,
        196,
        118
      ]
    },
    {
      "bbox": [
        0,
        70,
        53,
        104
      ]
    },
    {
      "bbox": [
        215,
        46,
        640,
        480
      ]
    }
  ]
}