{
  "ts": "2025-12-21T16:04:36.735Z",
  "frameId": 850,
  "motionPercent": 45.9619,
  "rois": [
    {
      "bbox": [
        443,
        452,
        483,
        480
      ]
    },
    {
      "bbox": [
        218,
        364,
        264,
        422
      ]
    },
    {
      "bbox": [
        0,
        58,
        372,
        385
      ]
    },
    {
      "bbox": [
        236,
        0,
        640,
        480
      ]
    },
    {
      "bbox": [
        8,
        0,
        125,
        63
      ]
    }
  ]
}