{
  "ts": "2025-12-21T17:25:27.539Z",
  "frameId": 56460,
  "motionPercent": 52.7946,
  "rois": [
    {
      "bbox": [
        613,
        289,
        639,
        350
      ]
    },
    {
      "bbox": [
        569,
        146,
        627,
        201
      ]
    },
    {
      "bbox": [
        478,
        143,
        505,
        204
      ]
    },
    {
      "bbox": [
        479,
        94,
        526,
        133
      ]
    },
    {
      "bbox": [
        450,
        0,
        617,
        480
      ]
    },
    {
      "bbox": [
        130,
        0,
        503,
        480
      ]
    },
    {
      "bbox": [
        499,
        224,
        559,
        284
      ]
    }
  ]
}